url_manager/__init__.py
url_manager/enum.py
url_manager/helper.py
url_manager/main.py
url_manager/social_media.py
url_manager-1.4.0.dist-info/METADATA
url_manager-1.4.0.dist-info/WHEEL
url_manager-1.4.0.dist-info/RECORD
