Metadata-Version: 2.1
Name: url-manager
Version: 1.4.0
Summary: 
Author: Bruno
Author-email: bruno.gluszczuk@pagar.me
Requires-Python: >=3.8.0,<4.0.0
Classifier: Programming Language :: Python :: 3
Classifier: Programming Language :: Python :: 3.8
Classifier: Programming Language :: Python :: 3.9
Classifier: Programming Language :: Python :: 3.10
Classifier: Programming Language :: Python :: 3.11
Classifier: Programming Language :: Python :: 3.12
Requires-Dist: validators (>=0.20.0,<0.21.0)
